nonebot_plugin_add_friends/__init__.py
nonebot_plugin_add_friends/config.py
nonebot_plugin_add_friends/event.py
nonebot_plugin_add_friends/matcher.py
nonebot_plugin_add_friends-0.1.5.dist-info/LICENSE
nonebot_plugin_add_friends-0.1.5.dist-info/METADATA
nonebot_plugin_add_friends-0.1.5.dist-info/WHEEL
nonebot_plugin_add_friends-0.1.5.dist-info/RECORD
