Metadata-Version: 2.3
Name: nonebot-plugin-add-friends
Version: 0.1.5
Summary: 处理好友申请和群邀请，支持查看申请、手动同意/拒绝申请、同意/拒绝全部申请。
Keywords: nonebot,nonebot2,plugin
Author: hakunomiko
Author-email: 48401273+hakunomiko@users.noreply.github.com
Requires-Python: >=3.9
Classifier: Programming Language :: Python :: 3
Classifier: Programming Language :: Python :: 3.9
Classifier: Programming Language :: Python :: 3.10
Classifier: Programming Language :: Python :: 3.11
Classifier: Programming Language :: Python :: 3.12
Classifier: Programming Language :: Python :: 3.13
Requires-Dist: nonebot-adapter-onebot (>=2.4.4)
Requires-Dist: nonebot2 (>=2.3.0,<3.0.0)
Requires-Dist: nonebot_plugin_localstore (>=0.7.1,<0.8.0)
Project-URL: Repository, https://github.com/hakunomiko/nonebot-plugin-add-friends
